top-level-ai/__init__.py
top-level-ai/__version__.py
top-level-ai/fancy_ai_core_tech.py
top_level_ai/__init__.py
top_level_ai/__version__.py
top_level_ai/fancy_ai_core_tech.py
top_level_ai-1.0.0.dist-info/LICENSE
top_level_ai-1.0.0.dist-info/METADATA
top_level_ai-1.0.0.dist-info/WHEEL
top_level_ai-1.0.0.dist-info/top_level.txt
top_level_ai-1.0.0.dist-info/RECORD
