Metadata-Version: 2.1
Name: top-level-ai
Version: 1.0.0
Summary: The world's top AI chat framework (just kidding).
Home-page: https://github.com/ZetaSp/top_level_ai
Author: Zetaspace
Author-email: zetaspace@outlook.com
License: WTFPL
Classifier: Development Status :: 1 - Planning
Classifier: Intended Audience :: Developers
Classifier: License :: Public Domain
Classifier: Natural Language :: Chinese (Simplified)
Classifier: Natural Language :: Chinese (Traditional)
Classifier: Natural Language :: English
Classifier: Operating System :: OS Independent
Classifier: Programming Language :: Python
Classifier: Programming Language :: Python :: 3
Classifier: Programming Language :: Python :: 3.6
Classifier: Programming Language :: Python :: Implementation :: CPython
Classifier: Topic :: Games/Entertainment :: Simulation
Requires-Python: >=3.6.0
License-File: LICENSE
